fdrtd/plugins/datashield/__init__.py
fdrtd/plugins/datashield/connection.py
fdrtd/plugins/datashield/helpers.py
fdrtd/plugins/datashield/login.py
fdrtd_datashield-0.5.0.dist-info/METADATA
fdrtd_datashield-0.5.0.dist-info/WHEEL
fdrtd_datashield-0.5.0.dist-info/top_level.txt
fdrtd_datashield-0.5.0.dist-info/RECORD
