Metadata-Version: 2.1
Name: fdrtd-datashield
Version: 0.5.0
Summary: Federated Secure Computing
Home-page: https://github.com/fdrtd
Author: bytes for life GmbH
Author-email: support@fdrtd.com
License: UNKNOWN
Platform: UNKNOWN
Classifier: Development Status :: 4 - Beta
Classifier: Intended Audience :: Developers
Classifier: Intended Audience :: Financial and Insurance Industry
Classifier: Intended Audience :: Healthcare Industry
Classifier: Intended Audience :: Information Technology
Classifier: Intended Audience :: Legal Industry
Classifier: Intended Audience :: Science/Research
Classifier: Intended Audience :: Telecommunications Industry
Classifier: License :: OSI Approved :: MIT License
Classifier: Natural Language :: English
Classifier: Operating System :: OS Independent
Classifier: Programming Language :: Python :: 3
Classifier: Topic :: Security
Classifier: Topic :: Security :: Cryptography
Classifier: Topic :: Software Development :: Libraries
Classifier: Topic :: Software Development :: Libraries :: Python Modules
Requires-Dist: fdrtd
Requires-Dist: fdrtd-server
Requires-Dist: functools
Requires-Dist: importlib
Requires-Dist: numpy
Requires-Dist: pathlib
Requires-Dist: rpy2
Requires-Dist: threading
Requires-Dist: uuid
